cmdbapi/__init__.py
cmdbapi/cmdbapi.py
cmdbapi-2.0.1.dist-info/LICENSE
cmdbapi-2.0.1.dist-info/METADATA
cmdbapi-2.0.1.dist-info/WHEEL
cmdbapi-2.0.1.dist-info/top_level.txt
cmdbapi-2.0.1.dist-info/RECORD
