Metadata-Version: 2.1
Name: cmdbapi
Version: 2.0.1
Summary: A short library for working CMDB API
Home-page: https://github.com/laspavel/cmdbapi
Author: Pavlo Lashkevych
Author-email: laspavel@gmail.com
License: UNKNOWN
Project-URL: Documentation, https://github.com/laspavel/cmdbapi/blob/master/README.md
Keywords: api cmdb
Platform: UNKNOWN
Classifier: Programming Language :: Python :: 3.6
Classifier: License :: OSI Approved :: MIT License
Classifier: Operating System :: OS Independent
Requires-Python: >=3.6
Requires-Dist: requests (>=2.25.1)
